canonical/config-options/__init__.py
canonical/config-options/common.py
canonical/config-options/_static/config-options.css
canonical/config-options/_static/config-options.js
canonical/contributor-listing/__init__.py
canonical/contributor-listing/common.py
canonical/contributor-listing/_static/contributors.css
canonical/contributor-listing/_static/contributors.js
canonical/custom-rst-roles/__init__.py
canonical/filtered-toc/__init__.py
canonical/related-links/__init__.py
canonical/related-links/common.py
canonical/related-links/_static/related-links.css
canonical/terminal-output/__init__.py
canonical/terminal-output/common.py
canonical/terminal-output/_static/terminal-output.css
canonical/ubuntu-images/__init__.py
canonical/ubuntu-images/common.py
canonical/youtube-links/__init__.py
canonical/youtube-links/common.py
canonical/youtube-links/_static/youtube.css
canonical_sphinx_extensions-0.0.34.dist-info/licenses/LICENSE
config-options/__init__.py
config-options/common.py
config-options/_static/config-options.css
config-options/_static/config-options.js
custom-rst-roles/__init__.py
filtered-toc/__init__.py
related-links/__init__.py
related-links/common.py
related-links/_static/related-links.css
terminal-output/__init__.py
terminal-output/common.py
terminal-output/_static/terminal-output.css
ubuntu-images/__init__.py
ubuntu-images/common.py
youtube-links/__init__.py
youtube-links/common.py
youtube-links/_static/youtube.css
canonical_sphinx_extensions-0.0.34.dist-info/METADATA
canonical_sphinx_extensions-0.0.34.dist-info/WHEEL
canonical_sphinx_extensions-0.0.34.dist-info/top_level.txt
canonical_sphinx_extensions-0.0.34.dist-info/RECORD
