Metadata-Version: 2.4
Name: canonical-sphinx-extensions
Version: 0.0.34
Summary: A collection of Sphinx extensions used by Canonical documentation
Home-page: https://github.com/canonical/canonical-sphinx-extensions
Author: Michael Park
Author-email: michael.park@canonical.com
Requires-Python: >=3.10
License-File: LICENSE
Requires-Dist: sphinx
Requires-Dist: requests
Requires-Dist: beautifulsoup4
Requires-Dist: docutils
Requires-Dist: gitpython
Dynamic: license-file
